{"data": null, "citingPaperInfo": {"openAccessPdf": {"url": "", "status": null, "license": null, "disclaimer": "Notice: The following paper fields have been elided by the publisher: {'references'}. Paper or abstract available at https://api.unpaywall.org/v2/10.1109/ICISS49785.2020.9315932?email=<INSERT_YOUR_EMAIL> or https://doi.org/10.1109/ICISS49785.2020.9315932, which is subject to the license by the author or copyright owner provided with this content. Please go to the source to verify the license and copyright information for your use."}, "title": "Insider Threat Detection using Deep Learning: A Review", "authors": [{"authorId": "2047246364", "name": "Madhu Raut"}, {"authorId": "9266339", "name": "S. Dhavale"}, {"authorId": "47264639", "name": "Ashutosh Kumar Singh"}, {"authorId": "66333213", "name": "A. Mehra"}]}}