{"data": null, "citingPaperInfo": {"openAccessPdf": {"url": "", "status": "CLOSED", "license": null, "disclaimer": "Notice: The following paper fields have been elided by the publisher: {'references'}. Paper or abstract available at https://api.unpaywall.org/v2/10.1007/978-3-319-98842-9_6?email=<INSERT_YOUR_EMAIL> or https://doi.org/10.1007/978-3-319-98842-9_6, which is subject to the license by the author or copyright owner provided with this content. Please go to the source to verify the license and copyright information for your use."}, "title": "Machine Learning Algorithms for Network Intrusion Detection", "authors": [{"authorId": "2155869373", "name": "Jie Li"}, {"authorId": "144666283", "name": "Yanpeng Qu"}, {"authorId": "2864709", "name": "F. Chao"}, {"authorId": "2840036", "name": "Hubert P. H. Shum"}, {"authorId": "2882496", "name": "Edmond S. L. Ho"}, {"authorId": "1706028", "name": "Longzhi Yang"}]}}