{"data": null, "citingPaperInfo": {"openAccessPdf": {"url": "https://eprints.staffs.ac.uk/4758/1/IoT_IDS_Final__Copy_%20%28002%29.pdf", "status": "GREEN", "license": "other-oa", "disclaimer": "Notice: The following paper fields have been elided by the publisher: {'references'}. Paper or abstract available at https://api.unpaywall.org/v2/10.1109/COMST.2018.2844742?email=<INSERT_YOUR_EMAIL> or https://doi.org/10.1109/COMST.2018.2844742, which is subject to the license by the author or copyright owner provided with this content. Please go to the source to verify the license and copyright information for your use."}, "title": "A Critical Review of Practices and Challenges in Intrusion Detection Systems for IoT: Toward Universal and Resilient Systems", "authors": [{"authorId": "2026975", "name": "E. Benkhelifa"}, {"authorId": "144786291", "name": "T. Welsh"}, {"authorId": "1744086", "name": "W. Hamouda"}]}}